shitgram/__init__.py
shitgram/bot.py
shitgram/enums.py
shitgram/utils.py
shitgram/exceptions/__init__.py
shitgram/exceptions/api_exception.py
shitgram/handlers/__init__.py
shitgram/handlers/on_callback_query.py
shitgram/handlers/on_channel_post.py
shitgram/handlers/on_chosen_inline_result.py
shitgram/handlers/on_edited_channel_post.py
shitgram/handlers/on_edited_message.py
shitgram/handlers/on_inline_query.py
shitgram/handlers/on_message.py
shitgram/handlers/on_update.py
shitgram/methods/__init__.py
shitgram/methods/answer_callback_query.py
shitgram/methods/close.py
shitgram/methods/copy_message.py
shitgram/methods/forward_message.py
shitgram/methods/get_me.py
shitgram/methods/logout.py
shitgram/methods/send_animation.py
shitgram/methods/send_audio.py
shitgram/methods/send_document.py
shitgram/methods/send_location.py
shitgram/methods/send_media_group.py
shitgram/methods/send_message.py
shitgram/methods/send_photo.py
shitgram/methods/send_request.py
shitgram/methods/send_sticker.py
shitgram/methods/send_video.py
shitgram/methods/send_video_note.py
shitgram/methods/send_voice.py
shitgram/types/__init__.py
shitgram/types/animation.py
shitgram/types/audio.py
shitgram/types/callback_game.py
shitgram/types/callbackquery.py
shitgram/types/chat.py
shitgram/types/chat_administrator_rights.py
shitgram/types/chat_location.py
shitgram/types/chat_permissions.py
shitgram/types/chat_photo.py
shitgram/types/chat_shared.py
shitgram/types/contact.py
shitgram/types/dice.py
shitgram/types/document.py
shitgram/types/force_reply.py
shitgram/types/forum.py
shitgram/types/game.py
shitgram/types/inline_keyboard.py
shitgram/types/inline_query.py
shitgram/types/input_file.py
shitgram/types/input_media.py
shitgram/types/input_message_content.py
shitgram/types/invoice.py
shitgram/types/location.py
shitgram/types/login_url.py
shitgram/types/mention.py
shitgram/types/message.py
shitgram/types/message_auto_delete_timer_changed.py
shitgram/types/message_entity.py
shitgram/types/parser.py
shitgram-0.1.dev6.dist-info/LICENSE
shitgram-0.1.dev6.dist-info/METADATA
shitgram-0.1.dev6.dist-info/WHEEL
shitgram-0.1.dev6.dist-info/top_level.txt
shitgram-0.1.dev6.dist-info/RECORD
